{
  "30": {
    "contributors": {
      "0x36": 2,
      "0xeffeff@gmail.com": 1,
      "AlanStern": 20,
      "Benjamin-Block": 2,
      "Blub": 1,
      "ChaotianJing": 1,
      "ColinIanKing": 4,
      "FWei-HW": 4,
      "Fabo": 1,
      "Gnurou": 1,
      "GustavoARSilva": 6,
      "JasonYanHw": 1,
      "JianyuZhan": 1,
      "JoePerches": 3,
      "KNnut": 1,
      "Keno": 1,
      "LiJinyue": 1,
      "LorenzoBianconi": 3,
      "MJNowakowski": 1,
      "MSe1969": 1,
      "MatiasBjorling": 1,
      "Naoya-Horiguchi": 3,
      "NeoRaider": 1,
      "NicolasDichtel": 6,
      "Noctis-AKM": 1,
      "OGAWAHirofumi": 2,
      "PaulLawrenceGoogle": 1,
      "Pinglinux": 1,
      "RyanHsu": 3,
      "ScottyBauer": 1,
      "SinkFinder": 2,
      "Stricted": 3,
      "TaeheeYoo": 1,
      "TheCrazyLex": 2,
      "Villemoes": 3,
      "WOnder93": 1,
      "XNUBIA": 1,
      "a22543@motorola.com": 1,
      "a_katta@codeaurora.org": 1,
      "aagit": 1,
      "aarcange@redhat.com": 1,
      "abavanar@codeaurora.org": 2,
      "abdullahanam@codeaurora.org": 1,
      "abhikuma@codeaurora.org": 12,
      "abrestic": 1,
      "absingh@codeaurora.org": 6,
      "absingh@qti.qualcomm.com": 20,
      "achant@google.com": 1,
      "achouhan@codeaurora.org": 1,
      "acme@redhat.com": 4,
      "adekmaulana": 1,
      "adeshk@codeaurora.org": 1,
      "adhanoti@codeaurora.org": 5,
      "adobriyan@gmail.com": 1,
      "adriansm": 1,
      "adudani@google.com": 2,
      "agabbasov": 1,
      "agoswa@codeaurora.org": 3,
      "agruenba@redhat.com": 1,
      "airlied": 1,
      "ajitp@codeaurora.org": 1,
      "ajs1984": 2,
      "akappa@codeaurora.org": 5,
      "akhandav@codeaurora.org": 1,
      "akhandav@qti.qualcomm.com": 1,
      "akodanev": 4,
      "aksecurity": 1,
      "alesax": 1,
      "alevy@codeaurora.org": 1,
      "alexandrebelloni": 2,
      "alexandru-porosanu-nxp": 1,
      "alokkuma@codeaurora.org": 1,
      "amadeusz.slawinski@tieto.com": 1,
      "amir73il": 1,
      "amit.pundir@linaro.org": 1,
      "amluto": 1,
      "amwang@redhat.com": 1,
      "anadav": 1,
      "anajahi@codeaurora.org": 1,
      "andreyknvl@xxxxxxxxxx": 1,
      "andreym@codeaurora.org": 1,
      "aneela@codeaurora.org": 2,
      "anna-marialx": 2,
      "annamraj@codeaurora.org": 1,
      "anoobs": 2,
      "aotchere": 1,
      "archanar@qca.qualcomm.com": 4,
      "arco": 2,
      "ardbiesheuvel": 3,
      "arndb": 9,
      "aryabinin": 4,
      "asdil12": 1,
      "ashigarg@codeaurora.org": 1,
      "ashishka@codeaurora.org": 1,
      "ashishka@qti.qualcomm.com": 9,
      "asinghal@qca.qualcomm.com": 1,
      "atomlin1": 1,
      "aulanov": 1,
      "aunali1": 1,
      "avagin": 1,
      "avmenon@codeaurora.org": 1,
      "ayin@google.com": 1,
      "b-liu@ti.com": 1,
      "b32955@freescale.com": 1,
      "baohongliu": 1,
      "baruchsiach": 1,
      "ben.hutchings@codethink.co.uk": 3,
      "ben@armis.com": 1,
      "bentiss": 1,
      "benyxy@codeaurora.org": 3,
      "bernd-edlinger": 1,
      "bfields@redhat.com": 6,
      "bgoswami@codeaurora.org": 1,
      "bhe4": 1,
      "bigeasy@linutronix.de": 3,
      "bings@codeaurora.org": 13,
      "bjavvaji@codeaurora.org": 2,
      "bjking1": 1,
      "bjorn-helgaas": 1,
      "bkchan@codeaurora.org": 1,
      "bkomma@codeaurora.org": 1,
      "bmanoj@codeaurora.org": 7,
      "bmarzins": 1,
      "bmork": 1,
      "bongkyu.kim@lge.com": 1,
      "booxter": 1,
      "borkmann": 5,
      "borntraeger": 2,
      "bpoirier@suse.com": 2,
      "brauner": 2,
      "bromberg@codeaurora.org": 1,
      "broonie": 5,
      "bsegall@google.com": 1,
      "bsingharora": 1,
      "bthaler": 1,
      "bvanassche": 1,
      "bwhacks": 7,
      "byan@nvidia.com": 1,
      "byang-intel": 1,
      "c_asunka@qti.qualcomm.com": 1,
      "c_gowri@qti.qualcomm.com": 5,
      "c_hpothu@codeaurora.org": 3,
      "c_hpothu@qti.qualcomm.com": 4,
      "c_manjee@qti.qualcomm.com": 5,
      "c_medhar@qti.qualcomm.com": 2,
      "c_msapta@qti.qualcomm.com": 5,
      "c_nmasti@qti.qualcomm.com": 8,
      "c_rpappa@qti.qualcomm.com": 1,
      "c_rrachu@qti.qualcomm.com": 4,
      "c_saidir@qti.qualcomm.com": 2,
      "c_skonam@qti.qualcomm.com": 9,
      "cascardo@canonical.com": 1,
      "ccfries": 1,
      "ccooper@codeaurora.org": 1,
      "cdleonard": 1,
      "cernekee@chromium.org": 3,
      "cesarb": 1,
      "cgutman": 2,
      "chandanr": 3,
      "changbindu": 1,
      "charleskeepax": 2,
      "chaseyu": 2,
      "chazy": 1,
      "chenhuacai": 3,
      "chenjie6@huawei.com": 2,
      "chenweilong@huawei.com": 1,
      "chenyu56": 1,
      "chiaweic@codeaurora.org": 2,
      "chinmays@codeaurora.org": 1,
      "chleroy": 1,
      "chris.brand@broadcom.com": 1,
      "chris@sageembedded.com": 1,
      "chucklever": 1,
      "clyu": 1,
      "cmetcalf@ezchip.com": 1,
      "cmshekar@qti.qualcomm.com": 3,
      "colincross": 1,
      "colyli@suse.de": 1,
      "compudj": 1,
      "computersforpeace": 1,
      "congwang": 16,
      "cosmin21gs": 1,
      "covracer": 1,
      "cpaasch": 4,
      "cravin@codeaurora.org": 1,
      "credp": 1,
      "cyphar": 1,
      "d3zd3z": 1,
      "daehojeong": 2,
      "daeseokyoun": 2,
      "daidavid1@codeaurora.org": 2,
      "dan.carpenter@oracle.com": 20,
      "dan.forrest@ssec.wisc.edu": 1,
      "daniel-thompson": 1,
      "danielmentzgoogle": 3,
      "danvet": 1,
      "dasaris@qti.qualcomm.com": 1,
      "dave.martin@arm.com": 4,
      "dave@stgolabs.net": 5,
      "davem330": 3,
      "davidlohr@hp.com": 4,
      "deepthi@codeaurora.org": 1,
      "deesin@codeaurora.org": 1,
      "dendluri@codeaurora.org": 1,
      "dgloeck": 1,
      "dhowells": 4,
      "dianders": 1,
      "dikshita@codeaurora.org": 1,
      "diwic": 1,
      "djbw": 7,
      "djwong": 10,
      "dmitryfleytman": 1,
      "dmonakhov@openvz.org": 3,
      "dnlplm": 1,
      "dongyangli@ddn.com": 1,
      "douglascs@taghos.com.br": 1,
      "drosen@google.com": 14,
      "dsahern": 5,
      "dtor": 3,
      "duanj.fnst@cn.fujitsu.com": 3,
      "dundi@codeaurora.org": 2,
      "dvdhrm": 2,
      "dvlasenk": 1,
      "dvyukov": 2,
      "dwery": 1,
      "eafer": 1,
      "earlbread": 1,
      "ebiederm": 9,
      "ebiggers": 58,
      "eccopark": 1,
      "edumazet@google.com": 97,
      "efault@gmx.de": 1,
      "ekline": 1,
      "elaurent@google.com": 2,
      "eldad": 1,
      "elfring": 1,
      "elicooper@gmx.com": 2,
      "elp": 1,
      "emilne@redhat.com": 1,
      "eparis": 1,
      "ethan.zhao@oracle.com": 1,
      "fabf@skynet.be": 2,
      "fabio-porcedda": 1,
      "fabio.estevam@nxp.com": 1,
      "fabled": 3,
      "felipe.balbi@linux.intel.com": 2,
      "fengc@google.com": 3,
      "fengguang": 1,
      "ffainelli": 2,
      "ffusco@redhat.com": 1,
      "fishilico": 1,
      "fruggeri@arista.com": 1,
      "fruggeri@aristanetworks.com": 1,
      "furquan-goog": 1,
      "fw@strlen.de": 24,
      "fweisbec": 17,
      "g.nault@alphalink.fr": 45,
      "ganeshk@codeaurora.org": 2,
      "ganeshk@qti.qualcomm.com": 3,
      "gaofeng@cn.fujitsu.com": 3,
      "gaolez@codeaurora.org": 3,
      "gbian@codeaurora.org": 3,
      "gbian@qti.qualcomm.com": 3,
      "gby": 1,
      "geert+renesas@glider.be": 1,
      "geertu": 2,
      "gemorin": 1,
      "gfodi@codeaurora.org": 1,
      "gfreewind": 1,
      "gideondsouza": 1,
      "gilligan@aristanetworks.com": 1,
      "git@thegavinli.com": 1,
      "github-cygwin": 6,
      "gkathpal@codeaurora.org": 3,
      "glommer": 1,
      "gmogas@codeaurora.org": 1,
      "gormanm": 1,
      "govinds@codeaurora.org": 2,
      "govindsk85": 6,
      "grawity": 1,
      "greghackmann": 2,
      "gregkh": 4,
      "groeck": 2,
      "guaneryu": 1,
      "guiseny@codeaurora.org": 1,
      "gustavo.padovan@collabora.co.uk": 1,
      "guz.fnst@cn.fujitsu.com": 1,
      "gwshan@linux.vnet.ibm.com": 1,
      "haggertk": 2,
      "haibinl@codeaurora.org": 3,
      "hannes@stressinduktion.org": 5,
      "hans.verkuil@cisco.com": 11,
      "harya@codeaurora.org": 8,
      "hch@lst.de": 3,
      "hdeller": 1,
      "herbertx": 31,
      "heyitsanthony": 1,
      "heyunlei@huawei.com": 1,
      "hgeorge@codeaurora.org": 1,
      "himanaga@qti.qualcomm.com": 12,
      "himangi774": 1,
      "hisunil@codeaurora.org": 1,
      "hlrichardson": 1,
      "holtmann": 5,
      "hongsh@codeaurora.org": 1,
      "hongxu-jia": 1,
      "horiag": 1,
      "houpengyang@huawei.com": 2,
      "houtao1@huawei.com": 1,
      "hqu@codeaurora.org": 10,
      "hreinecke": 1,
      "hsahu@codeaurora.org": 1,
      "htejun": 8,
      "huanglianjun@vivo.com": 1,
      "hughd@google.com": 2,
      "huw@codeaurora.org": 3,
      "huw@qti.qualcomm.com": 1,
      "hverkuil": 2,
      "hyogi.gim@lge.com": 1,
      "iamkafai": 2,
      "ickle": 1,
      "idolf@google.com": 1,
      "idosch": 2,
      "ij1": 1,
      "info@stricted.net": 1,
      "j-c-h": 5,
      "j00ru": 1,
      "ja@ssi.bg": 4,
      "jahogan": 1,
      "james-morse-arm": 2,
      "james.bottomley@hansenpartnership.com": 1,
      "jamesyonan": 1,
      "jankara": 13,
      "javelinanddart": 2,
      "jazzguitar81": 2,
      "jbainbri": 1,
      "jbires@google.com": 1,
      "jc-boyd": 1,
      "jcliang@chromium.org": 1,
      "jdelvare": 1,
      "jeff-t-johnson": 1,
      "jengelh": 1,
      "jeremy-compostella": 1,
      "jeremycline": 2,
      "jerrylee@qnap.com": 1,
      "jge@codeaurora.org": 8,
      "jglisse@redhat.com": 1,
      "jgunthorpe": 2,
      "jhedberg": 2,
      "jhovold": 9,
      "jhsmt": 1,
      "jiacwu@codeaurora.org": 2,
      "jiad@codeaurora.org": 1,
      "jianminz@codeaurora.org": 5,
      "jie@chenjie6@huwei.com": 1,
      "jilin@nvidia.com": 1,
      "jim.dickerson@hpe.com": 1,
      "jing.xia@spreadtrum.com": 1,
      "jinweic@codeaurora.org": 1,
      "jitiphil@codeaurora.org": 2,
      "jiufei.xue@linux.alibaba.com": 1,
      "jjohnson@codeaurora.org": 10,
      "jkbs@redhat.com": 1,
      "jkosina@suse.cz": 1,
      "jlinton": 1,
      "jmaxwell37@gmail.com": 1,
      "jmberg": 15,
      "joe-lawrence": 3,
      "joelaf@google.com": 1,
      "joelagnel": 2,
      "joergroedel": 1,
      "joern@logfs.org": 1,
      "jolsa@redhat.com": 2,
      "jonathan.derrick@intel.com": 1,
      "jonernst07@gmail.com": 1,
      "jpoimboe": 1,
      "jprakash@codeaurora.org": 1,
      "jscherpelz@google.com": 1,
      "jslaby@suse.cz": 4,
      "jsolnit@google.com": 2,
      "jtlayton": 1,
      "jtpittman195": 1,
      "jukkar": 1,
      "jun.zhang@intel.com": 1,
      "jviki": 1,
      "jwerner-chromium": 2,
      "kabilank@qca.qualcomm.com": 3,
      "kal.conley@dectris.com": 1,
      "kaliu@codeaurora.org": 2,
      "kaliu@qti.qualcomm.com": 2,
      "kandoiruchi@google.com": 1,
      "kangxu@codeaurora.org": 1,
      "kapgupta@codeaurora.org": 5,
      "kapgupta@qti.qualcomm.com": 20,
      "kchen@synology.com": 1,
      "kees": 3,
      "keh@codeaurora.org": 2,
      "kernel@linuxace.com": 1,
      "kernelslacker": 2,
      "kgunda@codeaurora.org": 1,
      "khandual@linux.vnet.ibm.com": 1,
      "khazhyk": 1,
      "kheiss": 1,
      "khoroshilov": 1,
      "kilobyte": 1,
      "kirill.shutemov@linux.intel.com": 2,
      "kjli@qti.qualcomm.com": 1,
      "kkamagui": 2,
      "kknatara@qca.qualcomm.com": 11,
      "klokere@qca.qualcomm.com": 1,
      "kmani@codeaurora.org": 2,
      "koct9i": 8,
      "kontar": 1,
      "kopasiak": 1,
      "kopasiak90@gmail.com": 1,
      "kosaki": 2,
      "kraigatgoog": 1,
      "krzk": 2,
      "kseelam@qti.qualcomm.com": 4,
      "ksoni@qca.qualcomm.com": 1,
      "kuba-moo": 1,
      "kunleiz@codeaurora.org": 1,
      "kurva@codeaurora.org": 1,
      "kyeongdon.kim@lge.com": 1,
      "l.stelmach@samsung.com": 1,
      "labbott": 2,
      "lance.richardson.net@gmail.com": 1,
      "larsclausen": 1,
      "lategoodbye": 1,
      "lbai@codeaurora.org": 3,
      "lcolitti": 16,
      "lczerner": 4,
      "ldv-alt": 1,
      "leitao": 1,
      "leochang@codeaurora.org": 1,
      "liangwei@codeaurora.org": 6,
      "liangwei@qti.qualcomm.com": 8,
      "liaor@codeaurora.org": 2,
      "libin2015": 1,
      "lifeng@codeaurora.org": 7,
      "lifeng@qti.qualcomm.com": 1,
      "lihual@codeaurora.org": 2,
      "linusw": 3,
      "linux@dominikbrodowski.net": 1,
      "lirongqing@baidu.com": 1,
      "liuhangbin": 5,
      "lizf-os": 3,
      "lkml14@scotdoyle.com": 1,
      "lkundrak": 1,
      "longlimsft": 2,
      "lorenzo.pieralisi@arm.com": 1,
      "luis.henriques@canonical.com": 2,
      "luk1337": 1,
      "lunn": 1,
      "lxin": 7,
      "lyakh": 1,
      "m-chong": 1,
      "maco@android.com": 2,
      "macro@mips.com": 1,
      "madisuma@codeaurora.org": 1,
      "maggarwa@codeaurora.org": 1,
      "maheshb@google.com": 1,
      "manuels": 1,
      "maowenan@huawei.com": 1,
      "marc.zyngier@arm.com": 3,
      "marceloleitner": 3,
      "marissaw@google.com": 1,
      "mark.rutland@arm.com": 9,
      "martin.petersen@oracle.com": 2,
      "martinezjavier": 1,
      "martingkelly": 2,
      "masakazu.mokuno@gmail.com": 1,
      "mathias.krause@secunet.com": 1,
      "matnyman": 7,
      "mauricfo@linux.vnet.ibm.com": 1,
      "maurizio-lombardi": 1,
      "maxime.jayat@mobile-devices.fr": 1,
      "mchehab": 3,
      "mgorman@suse.de": 4,
      "mhiramat": 2,
      "mhocko@suse.com": 4,
      "mhocko@suse.cz": 1,
      "michael.opdenacker@free-electrons.com": 1,
      "michaelweiser": 2,
      "mike.pecovnik@gmail.com": 1,
      "mikeNG": 1,
      "mikechristie": 1,
      "milabs": 1,
      "minchank": 1,
      "ming1": 1,
      "mingo@kernel.org": 1,
      "minimaxwell": 1,
      "minliu@codeaurora.org": 5,
      "misterikkit": 1,
      "mita": 1,
      "mitchelh@codeaurora.org": 1,
      "mjamaloney": 1,
      "mjavid@codeaurora.org": 10,
      "mkalikot@qca.qualcomm.com": 1,
      "mkarhumaa": 1,
      "mkbestas@lineageos.org": 1,
      "mkerrisk": 8,
      "mkshah@codeaurora.org": 1,
      "mkubecek": 3,
      "mohamed.khadri@lge.com": 1,
      "mohicks": 1,
      "monty_pavel@sina.com": 1,
      "morbidrsa": 3,
      "mpatocka@redhat.com": 3,
      "mrv@mojatatu.com": 1,
      "mschlaegl": 1,
      "msivasub@codeaurora.org": 1,
      "msriram@codeaurora.org": 3,
      "mszeredi@redhat.com": 7,
      "mszeredi@suse.cz": 3,
      "mtesar-rh": 1,
      "mtharu@codeaurora.org": 3,
      "mukul@codeaurora.org": 3,
      "mukul@qti.qualcomm.com": 4,
      "mwang@codeaurora.org": 1,
      "mypopydev": 1,
      "nablio3000": 2,
      "naggar@codeaurora.org": 2,
      "namhyung.kim@lge.com": 1,
      "namjaejeon": 2,
      "natesully": 1,
      "nathanchance": 1,
      "naveenramaraj": 1,
      "nbd168": 1,
      "ncardwell@google.com": 4,
      "neeraju@codeaurora.org": 3,
      "neersoni@codeaurora.org": 1,
      "neilb@suse.com": 2,
      "neilzhang1123@hotmail.com": 1,
      "nickdesaulniers": 1,
      "nicstange": 3,
      "niklas.soderlund+renesas@ragnatech.se": 1,
      "nikolay@cumulusnetworks.com": 9,
      "nikolay@redhat.com": 1,
      "niteshs@codeaurora.org": 3,
      "niteshs@qti.qualcomm.com": 1,
      "nkachh@codeaurora.org": 1,
      "nkachhwa@codeaurora.org": 1,
      "nkukade@codeaurora.org": 3,
      "nlynch-mentor": 1,
      "nnshah@qti.qualcomm.com": 6,
      "norov": 1,
      "notro": 1,
      "noureddine@aristanetworks.com": 1,
      "nrawat@qca.qualcomm.com": 2,
      "nwnk": 1,
      "olsajiri": 3,
      "oneukum": 3,
      "oneukum@suse.de": 1,
      "oniko": 1,
      "oohal": 1,
      "opendmb@gmail.com": 1,
      "osandov": 1,
      "ozbenh": 1,
      "pabeni@redhat.com": 11,
      "panand@redhat.com": 2,
      "paroj": 1,
      "pauld@redhat.com": 1,
      "paulz@codeaurora.org": 4,
      "pcmoore": 4,
      "pdxChen": 1,
      "peda-r": 1,
      "penguin-kernel@i-love.sakura.ne.jp": 5,
      "peterhurley": 1,
      "peterz@infradead.org": 18,
      "petrvandrovec": 1,
      "phil.turnbull@oracle.com": 1,
      "phueber@kernsp.in": 1,
      "pihsun@chromium.org": 1,
      "pillair@codeaurora.org": 1,
      "pinguin255@gmail.com": 1,
      "pkomandu@codeaurora.org": 1,
      "po-hsu.lin@canonical.com": 1,
      "prakashp@qca.qualcomm.com": 3,
      "pranjas": 1,
      "pratapn@codeaurora.org": 1,
      "prathampratap@codeaurora.org": 1,
      "preeti@linux.vnet.ibm.com": 1,
      "priv.luk@gmail.com": 1,
      "prkrishn@codeaurora.org": 1,
      "prsood@codeaurora.org": 1,
      "pshelar": 1,
      "pxu@qti.qualcomm.com": 1,
      "qiliu@codeaurora.org": 1,
      "qsn": 9,
      "quentin.casasnovas@oracle.com": 1,
      "quiche@google.com": 1,
      "qunz@codeaurora.org": 2,
      "quobert": 1,
      "rabinv": 2,
      "rafael.j.wysocki@intel.com": 2,
      "rajeshk@codeaurora.org": 1,
      "rajmal.menariya@spreadtrum.com": 1,
      "rambad@codeaurora.org": 4,
      "ramosian-glider": 7,
      "ranj063": 1,
      "raphaelsc": 1,
      "raphnet": 1,
      "rashika": 1,
      "ravij": 1,
      "ravisadineni@chromium.org": 1,
      "rbindra@codeaurora.org": 1,
      "rchennak@codeaurora.org": 1,
      "rdna": 1,
      "rdunlap@infradead.org": 1,
      "realmz": 1,
      "ribalda": 1,
      "richardweinberger": 5,
      "ridgek": 1,
      "rientjes@google.com": 2,
      "rikardfalkeborn": 1,
      "rikvanriel": 1,
      "riteshh@codeaurora.org": 2,
      "rmk+kernel@armlinux.org.uk": 5,
      "rmurphy-arm": 1,
      "rodrigorc": 1,
      "rohit.kr@samsung.com": 1,
      "romieu@fr.zoreil.com": 1,
      "ronnychevalier": 1,
      "ross.zwisler@linux.intel.com": 1,
      "rostedt": 7,
      "roy.qing.li@gmail.com": 1,
      "rpatkar@codeaurora.org": 1,
      "rsirasan@codeaurora.org": 4,
      "rsirasan@qti.qualcomm.com": 1,
      "ruiwang1": 2,
      "rustyrussell": 2,
      "sachin.kamat@linaro.org": 1,
      "sahn@qti.qualcomm.com": 1,
      "sahuja@codeaurora.org": 2,
      "sahuja@qti.qualcomm.com": 2,
      "saidir@codeaurora.org": 10,
      "sakari.ailus@linux.intel.com": 3,
      "salvatore.benedetto@intel.com": 1,
      "salyzyn@google.com": 1,
      "sancha@codeaurora.org": 1,
      "sandeen@redhat.com": 1,
      "santhoshbehara@codeaurora.org": 1,
      "sbohrer@rgmadvisors.com": 3,
      "sbrivio@redhat.com": 4,
      "schikk@codeaurora.org": 1,
      "sdash@codeaurora.org": 1,
      "sergei.shtylyov@cogentembedded.com": 1,
      "sergey-senozhatsky": 2,
      "sergey.senozhatsky.work@gmail.com": 2,
      "serhepopovych": 1,
      "sgirigow@codeaurora.org": 27,
      "sgirigow@qca.qualcomm.com": 5,
      "sgorle@codeaurora.org": 1,
      "sgoud@codeaurora.org": 3,
      "sgownipa@codeaurora.org": 2,
      "sgrover@codeaurora.org": 1,
      "sgruszka": 1,
      "shaibal.dutta@broadcom.com": 5,
      "shaibal.dutta@linaro.org": 1,
      "shakeelb": 1,
      "shawnguo2": 1,
      "shemminger": 2,
      "shjain@codeaurora.org": 1,
      "shligit": 1,
      "shmulik@metanetworks.com": 1,
      "shmull": 1,
      "shuox.liu@intel.com": 1,
      "siddpodd@codeaurora.org": 5,
      "siddpodd@qti.qualcomm.com": 4,
      "simon.horman@netronome.com": 1,
      "siqilin@google.com": 1,
      "sivaa@codeaurora.org": 1,
      "sjanc": 1,
      "skonam@codeaurora.org": 4,
      "skpadma@codeaurora.org": 5,
      "skpadma@qti.qualcomm.com": 19,
      "smanag@codeaurora.org": 3,
      "smore-lore": 2,
      "smuellerDD": 2,
      "smullati@codeaurora.org": 2,
      "smullati@qti.qualcomm.com": 3,
      "snitm": 2,
      "soheilhy": 2,
      "spyffe@google.com": 1,
      "sramana@codeaurora.org": 1,
      "sriramr@arista.com": 1,
      "srivatsa.bhat@linux.vnet.ibm.com": 2,
      "sselvara@codeaurora.org": 4,
      "sselvara@qti.qualcomm.com": 11,
      "ssuryaputra": 1,
      "standby24x7": 1,
      "steffen-maier": 4,
      "steffen.klassert@secunet.com": 6,
      "stephensmalley": 1,
      "storulf": 1,
      "stranche@codeaurora.org": 1,
      "stummala@codeaurora.org": 1,
      "subashab@codeaurora.org": 1,
      "sudipm-mukherjee": 1,
      "sunilravi@google.com": 1,
      "suzuki.poulose@arm.com": 1,
      "syphyr": 2506,
      "syphyr@gmail.com": 79,
      "tahsin@google.com": 1,
      "tbhardwa@codeaurora.org": 1,
      "tehcaster": 6,
      "test.tberghammer@gmail.com": 1,
      "tfyu@codeaurora.org": 12,
      "tglx@linutronix.de": 10,
      "thejh": 11,
      "thomas.goff@ll.mit.edu": 1,
      "thornber@redhat.com": 1,
      "tiffany.lin@mediatek.com": 1,
      "timmurray@google.com": 3,
      "tinlin@codeaurora.org": 24,
      "tititiou36": 1,
      "tiwai": 56,
      "tkhai": 2,
      "tkjos@android.com": 1,
      "tklauser": 1,
      "tmlind": 1,
      "toddkjos": 2,
      "tomasz1986": 1,
      "tomratbert": 1,
      "tonyj@suse.de": 1,
      "torvalds": 16,
      "toshikani": 1,
      "tpetazzoni": 1,
      "trashsee": 1,
      "trbecker": 1,
      "trondmypd": 1,
      "tstrudel@google.com": 16,
      "tyhicks": 1,
      "tytso": 59,
      "ummakynes": 1,
      "urezki": 1,
      "utrace": 45,
      "vaibhav92": 1,
      "vasilykh@arista.com": 1,
      "vaverin": 9,
      "vballa@codeaurora.org": 1,
      "vbucha@codeaurora.org": 5,
      "vcgomes": 1,
      "vdavydov@parallels.com": 1,
      "vegard": 8,
      "vgarodia": 1,
      "vigneshk@codeaurora.org": 3,
      "vinayakmenon": 1,
      "vinmenon@codeaurora.org": 4,
      "vireshk": 7,
      "viro@zeniv.linux.org.uk": 19,
      "viswanat@codeaurora.org": 6,
      "vkalia@codeaurora.org": 1,
      "vkanchan@qti.qualcomm.com": 2,
      "vkommara@codeaurora.org": 1,
      "vlad902": 1,
      "vladimir.murzin@arm.com": 1,
      "vladimir_zapolskiy@mentor.com": 2,
      "vnagarnaik": 1,
      "vstehle": 1,
      "vtanuku@codeaurora.org": 2,
      "vtl": 1,
      "vtumati@codeaurora.org": 1,
      "vvalluru@codeaurora.org": 1,
      "vviswana@codeaurora.org": 2,
      "vyeturu@qca.qualcomm.com": 3,
      "vzapolskiy": 2,
      "w@1wt.eu": 9,
      "wadesong@codeaurora.org": 6,
      "wang6495@umn.edu": 2,
      "wangkefeng.wang@huawei.com": 1,
      "wdebruij": 16,
      "weijie.yang@samsung.com": 1,
      "weivincewang": 1,
      "weiwan@google.com": 5,
      "weiyongjun1@huawei.com": 1,
      "wenjianhn": 2,
      "westeri": 2,
      "wildea01": 11,
      "wilhuang@codeaurora.org": 2,
      "wmanley": 1,
      "wr0112358": 2,
      "wugao@codeaurora.org": 2,
      "wugao@qti.qualcomm.com": 3,
      "xiaogang@codeaurora.org": 1,
      "xieyisheng1@huawei.com": 2,
      "xiongzhongjiang": 2,
      "xsang@codeaurora.org": 3,
      "yang.yang29@zte.com.cn": 1,
      "yangdongdong@xiaomi.com": 1,
      "yangerkun@huawei.com": 3,
      "yangx92@hotmail.com": 1,
      "yao.jin@linux.intel.com": 1,
      "ycheng@google.com": 5,
      "ycnian": 1,
      "yintang@codeaurora.org": 4,
      "yintang@qti.qualcomm.com": 5,
      "yizeng@asrmicro.com": 1,
      "yongjun_wei@trendmicro.com.cn": 1,
      "ysriramg@codeaurora.org": 2,
      "yu.c.chen@intel.com": 1,
      "yuehaibing@huawei.com": 5,
      "yupeng0921": 1,
      "yyuwang@codeaurora.org": 3,
      "yzkqfll": 1,
      "zaitcev@redhat.com": 1,
      "zenczykowski": 1,
      "zevweiss": 1,
      "zfding": 5,
      "zhangq@codeaurora.org": 9,
      "zhangq@qti.qualcomm.com": 8,
      "zhangyi089": 1,
      "zhao-gang": 1,
      "zhaoyang@codeaurora.org": 2,
      "zhenzhang.zhang@huawei.com": 1,
      "zkong@codeaurora.org": 1,
      "zlpnobody@gmail.com": 3,
      "zonque": 1,
      "zoran.markovic@linaro.org": 1,
      "zx2c4": 3
    },
    "n_commits": 2513,
    "n_contributors": 821
  },
  "180": {
    "contributors": {
      "BadDaemon": 4,
      "Claymore1297": 1,
      "Harinus": 1,
      "Sekilsgs2": 18,
      "Stricted": 34,
      "Usaamah99": 2,
      "baddaemon87@gmail.com": 4,
      "basilgello": 4,
      "haggertk": 5,
      "ivanmeler": 3,
      "javelinanddart": 2,
      "luk1337": 9,
      "mikeNG": 9,
      "mkbestas@lineageos.org": 9,
      "priv.luk@gmail.com": 6,
      "raymanfx": 2,
      "timmurray@google.com": 1
    },
    "n_commits": 57,
    "n_contributors": 17
  },
  "365": {
    "contributors": {
      "AlanStern": 2,
      "BadDaemon": 2,
      "Demon000": 2,
      "Harinus": 1,
      "Lukas0610": 1,
      "Stricted": 21,
      "abavanar@codeaurora.org": 2,
      "abhikuma@codeaurora.org": 4,
      "adhanoti@codeaurora.org": 2,
      "alviteri": 1,
      "amitmahajan@google.com": 1,
      "amluto": 1,
      "baddaemon87@gmail.com": 1,
      "basilgello": 1,
      "bgcngm": 6,
      "bgcngm@gmail.com": 1,
      "bjavvaji@codeaurora.org": 6,
      "c_hpothu@qti.qualcomm.com": 2,
      "codeworkx": 1,
      "danwood76": 1,
      "dianlujitao": 2,
      "drosen@google.com": 16,
      "dtor": 2,
      "ebiggers": 2,
      "edumazet@google.com": 4,
      "ericrannaud": 1,
      "etancohen@google.com": 1,
      "fengc@google.com": 2,
      "fourkbomb": 2,
      "freak97": 1,
      "gnehzuil": 3,
      "gohulanb@codeaurora.org": 1,
      "gohulanb@quicinc.com": 1,
      "gregkh": 2,
      "haggertk": 4,
      "hansson@google.com": 1,
      "i_ivan@windowslive.com": 12,
      "info@stricted.net": 10,
      "intervigilium": 3,
      "ivanmeler": 15,
      "javelinanddart": 1,
      "javelinanddart@gmail.com": 1,
      "jazzguitar81": 2,
      "jeffvanderstoep": 3,
      "jerpelea": 2,
      "jhovold": 2,
      "keh@codeaurora.org": 2,
      "luk1337": 72,
      "lxin": 2,
      "maniac103": 1,
      "mathieuchartier": 1,
      "mikeNG": 13,
      "mkbestas@lineageos.org": 10,
      "mpq@google.com": 1,
      "mszeredi@suse.cz": 1,
      "nharold@google.com": 1,
      "niteshs@qti.qualcomm.com": 2,
      "priv.luk@gmail.com": 36,
      "rajathr@codeaurora.org": 1,
      "raymanfx": 2,
      "rpius@google.com": 3,
      "ruthwar@codeaurora.org": 1,
      "sgirigow@qca.qualcomm.com": 2,
      "smore-lore": 1,
      "subashab@codeaurora.org": 1,
      "syphyr": 6,
      "syphyr@gmail.com": 2,
      "terrycrhuang@google.com": 1,
      "tfyu@codeaurora.org": 6,
      "tiwai": 4,
      "tomcherry@google.com": 1,
      "torvalds": 2,
      "tyanh@google.com": 1,
      "viro@zeniv.linux.org.uk": 6,
      "viswanat@codeaurora.org": 6,
      "ycchen@google.com": 1,
      "zhangjerry@google.com": 1,
      "zkong@codeaurora.org": 2
    },
    "n_commits": 177,
    "n_contributors": 78
  }
}