{
  "14.1-20180210-unofficial-vince": 192,
  "14.1-20180216-unofficial-vince": 1,
  "14.1-20180218-unofficial-vince": 5,
  "14.1-20180304-unofficial-vince": 231,
  "14.1-20180309-unofficial-vince": 15,
  "14.1-20180708-unofficial-vince": 1,
  "14.1-20190102-m6note-by maps233": 1,
  "14.1-20190608-unofficial-vince": 4,
  "14.1-20190610-unofficial-vince": 1,
  "14.1-20190611-unofficial-vince": 2,
  "14.1-20190614-unofficial-vince": 3,
  "14.1-20190615-unofficial-vince": 2,
  "14.1-20190617-unofficial-vince": 17,
  "15.1-20180401-unofficial-vince": 187,
  "15.1-20180422-unofficial-vince": 4,
  "15.1-20180423-unofficial-vince": 5,
  "15.1-20180504-unofficial-vince": 13,
  "15.1-20180510-unofficial-vince": 13,
  "15.1-20180519-unofficial-vince": 9,
  "15.1-20180526-unofficial-vince": 64,
  "15.1-20180527-unofficial-vince": 3,
  "15.1-20180529-unofficial-vince": 6,
  "15.1-20180604-unofficial-vince": 3,
  "15.1-20180623-unofficial-vince": 23,
  "15.1-20180728-unofficial-vince": 47,
  "15.1-20180809-unofficial-vince": 32,
  "15.1-20180812-unofficial-vince": 8,
  "15.1-20180909-unofficial-vince": 25,
  "15.1-20181229-unofficial-vince": 1,
  "15.1-20181231-unofficial-vince": 59,
  "15.1-20190127-unofficial-vince": 1,
  "15.1-20190608-unofficial-vince": 1,
  "15.1-20190609-unofficial-vince": 1,
  "15.1-20190613-unofficial-vince": 1,
  "15.1-20190630-unofficial-vince": 1,
  "16.0-20181014-unofficial-vince": 2,
  "16.0-20181025-unofficial-vince": 1,
  "16.0-20181031-unofficial-vince": 12,
  "16.0-20181115-unofficial-vince": 14,
  "16.0-20181120-unofficial-vince": 1,
  "16.0-20181123-unofficial-vince": 2,
  "16.0-20181201-unofficial-vince": 8,
  "16.0-20181208-unofficial-vince": 4,
  "16.0-20181213-unofficial-vince": 34,
  "16.0-20181223-unofficial-vince": 1,
  "16.0-20181228-unofficial-vince": 1,
  "16.0-20190107-unofficial-vince": 17,
  "16.0-20190111-unofficial-vince": 375,
  "16.0-20190124-unofficial-vince": 6,
  "16.0-20190131-unofficial-vince": 8,
  "16.0-20190301-unofficial-vince": 28,
  "16.0-20190311-unofficial-vince": 232,
  "16.0-20190314-unofficial-vince": 108,
  "16.0-20190327-unofficial-vince": 4,
  "16.0-20190419-unofficial-vince": 2,
  "16.0-20190423-unofficial-vince": 316,
  "16.0-20190426-unofficial-vince": 1,
  "16.0-20190503-unofficial-vince": 1,
  "16.0-20190519-unofficial-vince": 58,
  "16.0-20190520-unofficial-vince": 289,
  "16.0-20190523-unofficial-vince": 6,
  "16.0-20190525-unofficial-vince": 1,
  "16.0-20190526-unofficial-vince": 1,
  "16.0-20190528-unofficial-vince": 3,
  "16.0-20190529-unofficial-vince": 1,
  "16.0-20190530-unofficial-vince": 147,
  "16.0-20190531-unofficial-vince": 487,
  "16.0-20190602-unofficial-vince": 6,
  "16.0-20190614-unofficial-vince": 5,
  "16.0-20190625-unofficial-vince": 1,
  "16.0-20190702-unofficial-vince": 33,
  "16.0-20190707-unofficial-vince": 1,
  "16.0-20190708-unofficial-vince": 8,
  "16.0-cold": 2,
  "16.0.0-vince": 8,
  "aosp_vince-userdebug 9 pq3a.190505.002 eng.navink.20190522.033716 test-keys": 1,
  "aosp_vince-userdebug 9 pq3a.190505.002 eng.navink.20190523.101348 test-keys": 5,
  "aosp_vince-userdebug 9 pq3a.190505.002 eng.root.20190526.143932 test-keys": 2,
  "aosp_vince-userdebug 9 pq3a.190505.002 eng.root.20190526.192659 test-keys": 79,
  "aosp_vince-userdebug 9 pq3a.190505.002 eng.root.20190529.102444 test-keys": 2,
  "aosp_vince-userdebug 9 pq3a.190505.002 eng.root.20190531.134147 test-keys": 1,
  "aosp_vince-userdebug 9 pq3a.190505.002 eng.root.20190531.212546 test-keys": 1,
  "aosp_vince-userdebug 9 pq3a.190505.002 eng.root.20190601.000325 test-keys": 66,
  "aosp_vince-userdebug 9 pq3a.190605.003 eng.root.20190608.233358 test-keys": 1,
  "aosp_vince-userdebug 9 pq3a.190605.003 eng.root.20190609.084314 test-keys": 91,
  "aosp_vince-userdebug 9 pq3a.190605.003 eng.root.20190612.210804 test-keys": 1,
  "aosp_vince-userdebug 9 pq3a.190605.003 eng.root.20190619.103754 test-keys": 1,
  "aosp_vince-userdebug 9 pq3a.190605.003 eng.root.20190623.100656 test-keys": 1,
  "aosp_vince-userdebug 9 pq3a.190705.003 eng.root.20190709.102855 test-keys": 1,
  "lineage_vince-userdebug 9 pq1a.181205.006 0e8586c35b test-keys": 1,
  "mos-9.0.0-beta5.0-vince": 1
}