{
  "30": {
    "contributors": {
      "arajguru@codeaurora.org": 1,
      "dan.carpenter@oracle.com": 2,
      "edumazet@google.com": 2,
      "elektroschmock": 34,
      "elektroschmock78@googlemail.com": 2,
      "feizhang@codeaurora.org": 1,
      "ftonello": 4,
      "github-cygwin": 1,
      "johnsonnolen@gmail.com": 1,
      "miaoqing-pan": 2,
      "npjohnson": 3,
      "rostedt": 2,
      "salyzyn@google.com": 2,
      "steve@cyngn.com": 1,
      "surenb@google.com": 2,
      "tfroidcoeur": 2,
      "tiwai": 6,
      "tuba@ece.ufl.edu": 2,
      "wenwen@cs.uga.edu": 2,
      "xsang@codeaurora.org": 2
    },
    "n_commits": 22,
    "n_contributors": 20
  },
  "180": {
    "contributors": {
      "AxelLin": 4,
      "BadDaemon": 2,
      "LorenzoBianconi": 4,
      "Myself5": 1,
      "SinkFinder": 4,
      "WOnder93": 4,
      "YoDevil": 2,
      "adyabr@google.com": 2,
      "arco": 4,
      "astrachan@google.com": 4,
      "aviraxp": 5,
      "benquike": 4,
      "bgcngm": 4,
      "bitbucket@online.de": 4,
      "bmanoj@codeaurora.org": 20,
      "bohu@google.com": 1,
      "bwhacks": 4,
      "chandanr": 4,
      "changbindu": 4,
      "danw": 2,
      "djwong": 4,
      "dmonakhov@openvz.org": 8,
      "doctaweeks": 3,
      "dongyangli@ddn.com": 4,
      "drosen@google.com": 4,
      "dsahern": 4,
      "dupin@google.com": 2,
      "dvdhrm": 12,
      "eafer": 4,
      "ebiggers": 4,
      "edumazet@google.com": 4,
      "elektroschmock": 718,
      "elektroschmock78@googlemail.com": 61,
      "elfring": 4,
      "erfanoabdi": 2,
      "gajare-codeaurora": 32,
      "gannimo": 8,
      "github-cygwin": 16,
      "gmogas@codeaurora.org": 4,
      "guptapi@codeaurora.org": 4,
      "hannes@stressinduktion.org": 4,
      "hansson@google.com": 6,
      "invisiblek": 2,
      "jack@suse.com": 4,
      "jankara": 20,
      "jeremy-compostella": 4,
      "jianminz@codeaurora.org": 4,
      "jmalinen": 4,
      "jmberg": 24,
      "johnsonnolen@gmail.com": 18,
      "johnstultz-work": 2,
      "jonathan.derrick@intel.com": 4,
      "jongwook@google.com": 2,
      "jrior001": 1,
      "jsharkey": 1,
      "jun.li@freescale.com": 4,
      "kalcutter": 4,
      "kholk": 3,
      "kunleiz@codeaurora.org": 4,
      "kyungsik.lee@lge.com": 6,
      "larsclausen": 4,
      "lczerner": 20,
      "maurizio-lombardi": 4,
      "mikeNG": 2,
      "mkarhumaa": 4,
      "monising@codeaurora.org": 4,
      "nagaradh@codeaurora.org": 4,
      "ngeoffray@google.com": 2,
      "nicknitewolf": 2,
      "nikolay@cumulusnetworks.com": 4,
      "nocry22": 2,
      "npjohnson": 65,
      "osandov": 4,
      "peskal@google.com": 2,
      "ppandit@redhat.com": 3,
      "pshelar": 4,
      "rajeshk@codeaurora.org": 8,
      "ramosian-glider": 4,
      "rkumbako@codeaurora.org": 1,
      "rmk+kernel@arm.linux.org.uk": 3,
      "rouming": 4,
      "sakari.ailus@linux.intel.com": 8,
      "sam3000": 3,
      "sandeen@redhat.com": 4,
      "shemminger": 4,
      "shijum@codeaurora.org": 3,
      "shinruhan@google.com": 2,
      "simon.wunderlich@s2003.tu-chemnitz.de": 4,
      "smalot@codeaurora.org": 4,
      "smitag@codeaurora.org": 1,
      "smore-lore": 2,
      "spyffe": 2,
      "ssuryaextr": 4,
      "steffen.klassert@secunet.com": 12,
      "stummala@codeaurora.org": 4,
      "suyj-fnst": 4,
      "syphyr": 4,
      "tlinder@codeaurora.org": 4,
      "tomcherry@google.com": 2,
      "tytso": 68,
      "urezki": 4,
      "utrace": 12,
      "vaverin": 36,
      "vbucha@codeaurora.org": 4,
      "vigneshk@codeaurora.org": 4,
      "viro@zeniv.linux.org.uk": 12,
      "vkathota": 4,
      "wanghai26@huawei.com": 4,
      "wdebruij": 4,
      "wildea01": 3,
      "youngguo18": 4,
      "yuehaibing@huawei.com": 4,
      "zaitcev": 4,
      "zhangyi089": 8,
      "zhfan@google.com": 2
    },
    "n_commits": 374,
    "n_contributors": 115
  },
  "365": {
    "contributors": {
      "0x36": 4,
      "Akianonymus": 4,
      "AlanStern": 16,
      "Badhri@google.com": 8,
      "Blub": 4,
      "ChaotianJing": 4,
      "ColinIanKing": 4,
      "CruzBishop": 2,
      "Demon000": 4,
      "Gioh-Kim": 4,
      "Gnurou": 4,
      "GustavoARSilva": 8,
      "JianyuZhan": 4,
      "JielHello": 4,
      "JoePerches": 24,
      "JoonsooKim": 20,
      "JuliaLawall": 4,
      "LorenzoBianconi": 4,
      "MatiasBjorling": 4,
      "TaeheeYoo": 4,
      "Thinh.Nguyen@synopsys.com": 8,
      "Villemoes": 4,
      "YangX92@hotmail.com": 4,
      "ZhengjunXing": 4,
      "a3a3el": 4,
      "aarpure@codeaurora.org": 4,
      "abdullahanam@codeaurora.org": 4,
      "adharmap@codeaurora.org": 4,
      "agopik@codeaurora.org": 4,
      "ai.c.c0der@gmail.com": 4,
      "akhandav@codeaurora.org": 4,
      "akodanev": 4,
      "akpm00": 8,
      "akumark@codeaurora.org": 8,
      "alexelder": 20,
      "alistair.strachan@imgtec.com": 1,
      "aman.deep@samsung.com": 4,
      "amluto": 1,
      "amwang@redhat.com": 4,
      "andreas@biessmann.de": 4,
      "aneela@codeaurora.org": 4,
      "aotchere": 4,
      "arco": 3,
      "ardbiesheuvel": 4,
      "arndb": 4,
      "arunks.linux@gmail.com": 4,
      "arve-android": 4,
      "aryabinin": 8,
      "astrachan@google.com": 1,
      "atomlin1": 4,
      "aviralg@codeaurora.org": 16,
      "aviraxp": 3,
      "b-liu@ti.com": 4,
      "baruchsiach": 4,
      "ben@armis.com": 4,
      "benyxy@codeaurora.org": 8,
      "bgcngm": 7,
      "bgoswami@codeaurora.org": 8,
      "biger410": 4,
      "bp@alien8.de": 4,
      "bp@suse.de": 4,
      "brauner": 4,
      "bromberg@codeaurora.org": 4,
      "broonie": 20,
      "chenjie6@huawei.com": 8,
      "christophjaeger": 4,
      "cl@linux.com": 4,
      "colincross": 8,
      "congwang": 12,
      "cpandya@codeaurora.org": 4,
      "d-cagle@codeaurora.org": 4,
      "d.hatayama@jp.fujitsu.com": 8,
      "dan.carpenter@oracle.com": 12,
      "danvet": 4,
      "datawolf": 4,
      "davem330": 12,
      "daveyoung": 4,
      "davidlohr.bueso@hp.com": 8,
      "dchinner@redhat.com": 4,
      "dev-harsh1998": 4,
      "dhowells": 8,
      "dianlujitao": 8,
      "digitalcircuit": 1,
      "digitalcircuit36939@gmail.com": 1,
      "dilipgudlur": 4,
      "dirk@gouders.net": 4,
      "djwong": 8,
      "dkatraga@codeaurora.org": 4,
      "dmonakhov@openvz.org": 4,
      "dsahern": 4,
      "dvoytik": 4,
      "dwalter@google.com": 4,
      "earlbread": 4,
      "ebiederm": 12,
      "ebiggers": 24,
      "edumazet@google.com": 148,
      "egrumbach": 4,
      "eladwexler": 4,
      "elektroschmock": 3809,
      "elektroschmock78@googlemail.com": 354,
      "eparis": 4,
      "ericrannaud": 1,
      "executerx": 1,
      "fabf@skynet.be": 8,
      "fabled": 4,
      "felipe.balbi@linux.intel.com": 12,
      "fengguang": 4,
      "franciscofranco": 16,
      "fransklaver": 4,
      "fshp": 4,
      "fw@strlen.de": 8,
      "g.nault@alphalink.fr": 8,
      "gajare-codeaurora": 4,
      "gang.chen@asianux.com": 12,
      "geert+renesas@linux-m68k.org": 4,
      "geertu": 4,
      "gemorin": 4,
      "ghostrider-reborn": 3,
      "gideondsouza": 8,
      "github-cygwin": 8,
      "gnehzuil": 3,
      "gobenji": 4,
      "greearb": 4,
      "gregkh": 4,
      "gustavo.padovan@collabora.co.uk": 4,
      "guz.fnst@cn.fujitsu.com": 4,
      "haggarwa@codeaurora.org": 4,
      "haibinl@codeaurora.org": 4,
      "haicheng.li@linux.intel.com": 4,
      "hdwivedi@codeaurora.org": 4,
      "hegdevasant": 4,
      "hemaprathaban": 2,
      "herbertx": 12,
      "hgeorge@codeaurora.org": 4,
      "himangi774": 4,
      "hnaz": 32,
      "holtmann": 16,
      "hsahu@codeaurora.org": 4,
      "htejun": 4,
      "hverkuil": 4,
      "ickle": 4,
      "idosch": 4,
      "ionut.m.alexa@gmail.com": 4,
      "ja@ssi.bg": 8,
      "jahogan": 4,
      "jankara": 36,
      "javelinanddart": 4,
      "jcrouse@codeaurora.org": 16,
      "jdelvare": 12,
      "jeffvanderstoep": 4,
      "jfrkuska": 4,
      "jg1.han@samsung.com": 124,
      "jgebben": 8,
      "jhedberg": 8,
      "jhovold": 4,
      "jhrycay": 4,
      "jhugo@codeaurora.org": 4,
      "jiangliu": 12,
      "jiufei.xue@linux.alibaba.com": 4,
      "jkosina@suse.cz": 4,
      "jmberg": 24,
      "jmtrivi": 3,
      "joaodias@google.com": 4,
      "joelaf@google.com": 1,
      "johnsonnolen@gmail.com": 27,
      "johnstultz-work": 4,
      "jscherpelz@google.com": 4,
      "jstralko": 4,
      "jsvaerke": 4,
      "junjiew@codeaurora.org": 4,
      "kanish@codeaurora.org": 12,
      "kbae@codeaurora.org": 4,
      "kees": 8,
      "khali@linux-fr.org": 4,
      "kuba-moo": 4,
      "kuirongw@codeaurora.org": 4,
      "labbott": 16,
      "laijs@cn.fujitsu.com": 8,
      "lcolitti": 4,
      "lczerner": 8,
      "linusw": 8,
      "linux@dominikbrodowski.net": 4,
      "liwanp@linux.vnet.ibm.com": 24,
      "lmark@codeaurora.org": 12,
      "lucastanure": 5,
      "lvaz@codeaurora.org": 4,
      "lxin": 20,
      "maarten.lankhorst@canonical.com": 16,
      "maco@android.com": 76,
      "maco@google.com": 36,
      "maowenan@huawei.com": 4,
      "markus@trippelsdorf.de": 4,
      "matnyman": 12,
      "mattw@codeaurora.org": 4,
      "mbohan@codeaurora.org": 4,
      "mcgrof@suse.com": 12,
      "mgorman@suse.de": 72,
      "mhocko@suse.cz": 24,
      "michael.opdenacker@free-electrons.com": 4,
      "mike.pecovnik@gmail.com": 4,
      "mikeNG": 3,
      "minchank": 12,
      "minimaxwell": 4,
      "mjavid@codeaurora.org": 4,
      "mkarhumaa": 4,
      "mkhaja@codeaurora.org": 4,
      "mmaret": 4,
      "mpatocka@redhat.com": 4,
      "mruck": 4,
      "msfjarvis": 4,
      "msivap@codeaurora.org": 4,
      "mszeredi@suse.cz": 1,
      "mtharu@codeaurora.org": 4,
      "mwang@codeaurora.org": 4,
      "myfluxi": 4,
      "nbd168": 8,
      "neobuddy89": 12,
      "nikolay@redhat.com": 4,
      "notro": 4,
      "npjohnson": 51,
      "nwnk": 4,
      "opendata26": 3,
      "pabeni@redhat.com": 28,
      "patrick@parcs.ath.cx": 4,
      "pattjin": 4,
      "paulgortmaker": 4,
      "paulmck": 360,
      "pcmoore": 24,
      "pdaly@codeaurora.org": 8,
      "peda-r": 4,
      "penguin-kernel@I-love.SAKURA.ne.jp": 20,
      "penguin-kernel@i-love.sakura.ne.jp": 12,
      "peterhurley": 8,
      "peterz@infradead.org": 56,
      "phaniu@codeaurora.org": 16,
      "pkamliya@codeaurora.org": 1,
      "pmladek": 36,
      "pranjas": 4,
      "pratapn@codeaurora.org": 4,
      "qsn": 8,
      "qwestduck": 4,
      "rafael.j.wysocki@intel.com": 8,
      "rago@google.com": 3,
      "rajmal.menariya@spreadtrum.com": 4,
      "rambad@codeaurora.org": 4,
      "ramosian-glider": 8,
      "rdeva31": 4,
      "rdna": 4,
      "rgbriggs": 16,
      "rientjes@google.com": 24,
      "rikvanriel": 12,
      "rkumbako@codeaurora.org": 3,
      "rob.jones@codethink.co.uk": 4,
      "rostedt": 32,
      "sbrivio@redhat.com": 8,
      "schivers@csc.com": 4,
      "sergey-senozhatsky": 8,
      "sgorle@codeaurora.org": 4,
      "sgrover@codeaurora.org": 4,
      "shaibal.dutta@broadcom.com": 20,
      "shaibal.dutta@linaro.org": 4,
      "shakeelb": 4,
      "sherryy@android.com": 28,
      "shijum@codeaurora.org": 9,
      "shimoday": 8,
      "simmip@codeaurora.org": 4,
      "snits": 4,
      "songjinshi@xiaomi.com": 4,
      "spapothi@codeaurora.org": 12,
      "sriramr@arista.com": 4,
      "srivatsa.bhat@linux.vnet.ibm.com": 8,
      "steffen.klassert@secunet.com": 4,
      "stephensmalley": 8,
      "sthibaul": 4,
      "stranche@codeaurora.org": 4,
      "subashab@codeaurora.org": 7,
      "suleiman@google.com": 1,
      "sultanxda@gmail.com": 4,
      "tairrzayev": 8,
      "tariq.x.saeed@oracle.com": 4,
      "tehcaster": 4,
      "teobaluta": 4,
      "tglx@linutronix.de": 4,
      "thejh": 8,
      "thestinger": 1,
      "tim.gardner@canonical.com": 4,
      "timmurray@google.com": 15,
      "tiwai": 8,
      "tkhai": 4,
      "tkjos@android.com": 28,
      "tklauser": 4,
      "tmlind": 4,
      "toddkjos": 128,
      "tomascus": 4,
      "torvalds": 20,
      "treding@nvidia.com": 4,
      "tsoni@codeaurora.org": 4,
      "tstrudel@google.com": 4,
      "tyhicks": 8,
      "tytso": 40,
      "ummakynes": 4,
      "utrace": 196,
      "vaverin": 4,
      "vbucha@codeaurora.org": 4,
      "vcgomes": 4,
      "vgarodia": 4,
      "vigneshk@codeaurora.org": 4,
      "vinmenon@codeaurora.org": 16,
      "vireshk": 28,
      "viro@zeniv.linux.org.uk": 17,
      "vstehle": 4,
      "vvalluru@codeaurora.org": 4,
      "walken-google": 8,
      "wdebruij": 8,
      "weivincewang": 4,
      "weiwan@google.com": 4,
      "wildea01": 8,
      "xsang@codeaurora.org": 4,
      "xu-yiping": 8,
      "ycchiam": 4,
      "ydroneaud": 5,
      "yuehaibing@huawei.com": 8,
      "yzkqfll": 8,
      "zenczykowski": 4,
      "zhangfeigao": 4,
      "zhangshuxiao@xiaomi.com": 1,
      "zhangwm@marvell.com": 4,
      "zhangyanfei@cn.fujitsu.com": 40,
      "zhe.he@windriver.com": 4,
      "zhenzhang.zhang@huawei.com": 8,
      "zhong@linux.vnet.ibm.com": 4,
      "zonque": 4
    },
    "n_commits": 1925,
    "n_contributors": 332
  }
}